smart_airdrops_claimer/__init__.py
smart_airdrops_claimer/base.py
smart_airdrops_claimer-0.1.3.dist-info/LICENSE
smart_airdrops_claimer-0.1.3.dist-info/METADATA
smart_airdrops_claimer-0.1.3.dist-info/WHEEL
smart_airdrops_claimer-0.1.3.dist-info/top_level.txt
smart_airdrops_claimer-0.1.3.dist-info/RECORD
