Metadata-Version: 2.1
Name: smart-airdrops-claimer
Version: 0.1.3
Summary: A package for airdrop automation.
Home-page: https://github.com/smartairdrops/smart-airdrops-claimer
Author: Hokireceh
Author-email: ads.hokireceh@gmail.com
Classifier: Programming Language :: Python :: 3
Classifier: License :: OSI Approved :: MIT License
Classifier: Operating System :: OS Independent
Requires-Python: >=3.6
License-File: LICENSE
Requires-Dist: colorama
Requires-Dist: requests
Requires-Dist: brotli
